exoanalyzer/__init__.py
exoanalyzer/data/__init__.py
exoanalyzer/data/query.py
exoanalyzer/plotter/__init__.py
exoanalyzer/util/__init__.py
exoanalyzer/util/data_util.py
exoanalyzer/util/readables.py
exoanalyzer-0.11.dist-info/LICENSE
exoanalyzer-0.11.dist-info/METADATA
exoanalyzer-0.11.dist-info/WHEEL
exoanalyzer-0.11.dist-info/top_level.txt
exoanalyzer-0.11.dist-info/RECORD
