Metadata-Version: 2.1
Name: exoanalyzer
Version: 0.11
Summary: Tool for processing and visualizing exoplanet data.
Home-page: https://github.com/finn-ellis/exoanalyzer
Author: Finn Ellis
Author-email: xfinnellisx@gmail.com
License: UNKNOWN
Project-URL: Bug Tracker, https://github.com/finn-ellis/exoanalyzer/issues
Platform: UNKNOWN
Classifier: Programming Language :: Python :: 3
Classifier: License :: OSI Approved :: GNU General Public License v3 (GPLv3)
Classifier: Operating System :: OS Independent
Requires-Python: >=3.8
License-File: LICENSE
Requires-Dist: pyvo
Requires-Dist: matplotlib
Requires-Dist: numpy
